innerself/__init__.py
innerself/_version.py
innerself/core.py
innerself/tests/__init__.py
innerself/tests/test_core.py
innerself-0.0.2.dist-info/LICENSE
innerself-0.0.2.dist-info/METADATA
innerself-0.0.2.dist-info/WHEEL
innerself-0.0.2.dist-info/top_level.txt
innerself-0.0.2.dist-info/RECORD
